test.py
cli/__init__.py
cli/main.py
frontend/lexy.py
frontend/main.py
frontend/middle.py
frontend/parsetab.py
frontend/percy.py
utils/logging.py
utils/nodes.py
flow_toolkit-0.0.1.dist-info/LICENSE
flow_toolkit-0.0.1.dist-info/METADATA
flow_toolkit-0.0.1.dist-info/WHEEL
flow_toolkit-0.0.1.dist-info/entry_points.txt
flow_toolkit-0.0.1.dist-info/top_level.txt
flow_toolkit-0.0.1.dist-info/RECORD
