Metadata-Version: 2.1
Name: flow-toolkit
Version: 0.0.1
Summary: CLI toolkit for Flow language, and integration with python.
Author-email: StealthyPanda <shaikm259@gmail.com>
License: MIT License
Keywords: flow,ML,DL
Classifier: License :: OSI Approved :: MIT License
Classifier: Programming Language :: Python
Classifier: Programming Language :: Python :: 3
Requires-Python: >=3.10
License-File: LICENSE
Requires-Dist: codexregius
Requires-Dist: argparse
Requires-Dist: ply
Requires-Dist: dulwich
